merkletreepy/MerkleTree.py
merkletreepy/__init__.py
merkletreepy-0.0.2.dist-info/LICENSE
merkletreepy-0.0.2.dist-info/METADATA
merkletreepy-0.0.2.dist-info/WHEEL
merkletreepy-0.0.2.dist-info/top_level.txt
merkletreepy-0.0.2.dist-info/RECORD
