Metadata-Version: 2.1
Name: merkletreepy
Version: 0.0.2
Summary: Python port of merkletreejs
Home-page: https://github.com/callistachang/merkletreepy
Author: Callista Chang
Author-email: changcallista@gmail.com
License: UNKNOWN
Project-URL: Bug Tracker, https://github.com/callistachang/merkletreepy/issues
Platform: UNKNOWN
Classifier: Programming Language :: Python :: 3
Classifier: License :: OSI Approved :: MIT License
Classifier: Operating System :: OS Independent
Requires-Python: >=3.6
License-File: LICENSE
